tspec/__init__.py
tspec/actions_assert.py
tspec/actions_http.py
tspec/actions_ui.py
tspec/actions_unreal.py
tspec/assets.py
tspec/auto_process.py
tspec/blender_client.py
tspec/cli.py
tspec/config.py
tspec/context.py
tspec/doctor_android.py
tspec/doctor_ios.py
tspec/doctor_selenium.py
tspec/errors.py
tspec/manual_loader.py
tspec/manual_model.py
tspec/mcp_server.py
tspec/merge.py
tspec/model.py
tspec/neko_client.py
tspec/parser.py
tspec/programmatic.py
tspec/pytest_reporting.py
tspec/registry.py
tspec/report_view.py
tspec/runner.py
tspec/spec_versions.py
tspec/templates.py
tspec/templating.py
tspec/tspec_z1.py
tspec/unity_client.py
tspec/validate.py
tspec/when_expr.py
tspec/assets/update.ps1
tspec/ui/agent_browser_driver.py
tspec/ui/appium_driver.py
tspec/ui/base.py
tspec/ui/playwright_driver.py
tspec/ui/pywinauto_driver.py
tspec/ui/selenium_driver.py
tspec/ui/selenium_utils.py
tspec_runner-1.1.1.dist-info/METADATA
tspec_runner-1.1.1.dist-info/WHEEL
tspec_runner-1.1.1.dist-info/entry_points.txt
tspec_runner-1.1.1.dist-info/licenses/LICENSE
tspec_runner-1.1.1.dist-info/RECORD
