Metadata-Version: 2.4
Name: tspec-runner
Version: 1.1.1
Summary: TSpec runner: Markdown + tspec fenced blocks for test automation (spec-versioned)
Author-email: tspec <devnull@example.com>
License: MIT
License-File: LICENSE
Keywords: appium,automation,blender,markdown,mcp,playwright,pywinauto,selenium,spec,testing,unity,yaml
Classifier: Development Status :: 3 - Alpha
Classifier: License :: OSI Approved :: MIT License
Classifier: Operating System :: OS Independent
Classifier: Programming Language :: Python :: 3
Classifier: Programming Language :: Python :: 3 :: Only
Requires-Python: >=3.11
Requires-Dist: jsonschema>=4.22.0
Requires-Dist: packaging>=24.1
Requires-Dist: pydantic>=2.7.0
Requires-Dist: pyyaml>=6.0.1
Requires-Dist: rich>=13.7.1
Requires-Dist: typer>=0.12.3
Provides-Extra: appium
Requires-Dist: appium-python-client>=4.0.0; extra == 'appium'
Provides-Extra: blender
Requires-Dist: httpx>=0.27.0; extra == 'blender'
Provides-Extra: dev
Requires-Dist: httpx>=0.27.0; extra == 'dev'
Requires-Dist: pytest-html>=4.1.0; extra == 'dev'
Requires-Dist: pytest>=8.2.0; extra == 'dev'
Requires-Dist: ruff>=0.5.0; extra == 'dev'
Provides-Extra: mcp
Requires-Dist: mcp<2,>=1.7; extra == 'mcp'
Provides-Extra: neko
Requires-Dist: httpx>=0.27.0; extra == 'neko'
Provides-Extra: playwright
Requires-Dist: playwright>=1.44.0; extra == 'playwright'
Provides-Extra: pywinauto
Requires-Dist: pywinauto>=0.6.8; extra == 'pywinauto'
Provides-Extra: report
Requires-Dist: pytest-html>=4.1.0; extra == 'report'
Requires-Dist: pytest>=8.2.0; extra == 'report'
Provides-Extra: selenium
Requires-Dist: selenium>=4.22.0; extra == 'selenium'
Provides-Extra: unity
Requires-Dist: httpx>=0.27.0; extra == 'unity'
